{
  "required": true,
  "minVersion": "0.8",
  "package": "blueduck.jellyfishing.mixin",
  "compatibilityLevel": "JAVA_17",
  "mixins": [
    "ArmorFeatureRendererMixin",
    "FluidBlockMixin",
    "PistonHandlerMixin",
    "PlayerEntityMixin",
    "StructurePoolsMixin",
    "access.EnchantmentTargetAccess",
    "access.StructurePoolAccess",
    "access.VillagerAccess"
  ],
  "client": [
    "client.HoneyBlockMixin"
  ],
  "server": [
    "DrownedEntityMixin"
  ],
  "injectors": {
    "defaultRequire": 1
  }
}